README.md
setup.py
pibeep/__init__.py
pibeep/beep.py
pibeep.egg-info/PKG-INFO
pibeep.egg-info/SOURCES.txt
pibeep.egg-info/dependency_links.txt
pibeep.egg-info/entry_points.txt
pibeep.egg-info/top_level.txt