Metadata-Version: 2.1
Name: pibeep
Version: 0.0.1.4
Summary: Buzzer utility for pi
Home-page: https://github.com/Tsangares/beep
Author-email: william.wyatt@cgu.edu
License: UNKNOWN
Platform: UNKNOWN
Classifier: Programming Language :: Python :: 3
Classifier: License :: OSI Approved :: MIT License
Classifier: Operating System :: OS Independent
Requires-Python: >=3.7
